LICENSE
README.md
setup.py
py_telegram_bot_api_framework/ABot.py
py_telegram_bot_api_framework/AHandler.py
py_telegram_bot_api_framework/AStorage.py
py_telegram_bot_api_framework/BotBasicHandler.py
py_telegram_bot_api_framework/SimpleFileStorage.py
py_telegram_bot_api_framework/__init__.py
py_telegram_bot_api_framework.egg-info/PKG-INFO
py_telegram_bot_api_framework.egg-info/SOURCES.txt
py_telegram_bot_api_framework.egg-info/dependency_links.txt
py_telegram_bot_api_framework.egg-info/requires.txt
py_telegram_bot_api_framework.egg-info/top_level.txt